reana_cluster/__init__.py
reana_cluster/config.py
reana_cluster/reana_backend.py
reana_cluster/utils.py
reana_cluster/version.py
reana_cluster/backends/__init__.py
reana_cluster/backends/kubernetes/__init__.py
reana_cluster/backends/kubernetes/k8s.py
reana_cluster/backends/kubernetes/templates/backend_conf.yaml
reana_cluster/backends/kubernetes/templates/config.yaml
reana_cluster/backends/kubernetes/templates/clusterrole/service-reader.yaml
reana_cluster/backends/kubernetes/templates/clusterrolebinding/service-reader.yaml
reana_cluster/backends/kubernetes/templates/deployments/cwl-default-worker.yaml
reana_cluster/backends/kubernetes/templates/deployments/db-template.yaml
reana_cluster/backends/kubernetes/templates/deployments/job-controller-template.yaml
reana_cluster/backends/kubernetes/templates/deployments/message-broker-template.yaml
reana_cluster/backends/kubernetes/templates/deployments/serial-default-worker.yaml
reana_cluster/backends/kubernetes/templates/deployments/server-template.yaml
reana_cluster/backends/kubernetes/templates/deployments/wdb-template.yaml
reana_cluster/backends/kubernetes/templates/deployments/workflow-controller-template.yaml
reana_cluster/backends/kubernetes/templates/deployments/workflow-monitor-template.yaml
reana_cluster/backends/kubernetes/templates/deployments/yadage-default-worker.yaml
reana_cluster/backends/kubernetes/templates/deployments/zeromq-msg-proxy-template.yaml
reana_cluster/backends/kubernetes/templates/ingress/reana-ingress.yaml
reana_cluster/backends/kubernetes/templates/services/db-template.yaml
reana_cluster/backends/kubernetes/templates/services/job-controller-template.yaml
reana_cluster/backends/kubernetes/templates/services/message-broker-template.yaml
reana_cluster/backends/kubernetes/templates/services/server-template.yaml
reana_cluster/backends/kubernetes/templates/services/wdb-template.yaml
reana_cluster/backends/kubernetes/templates/services/workflow-controller-template.yaml
reana_cluster-0.3.0.dist-info/METADATA
reana_cluster-0.3.0.dist-info/RECORD
reana_cluster-0.3.0.dist-info/WHEEL
reana_cluster-0.3.0.dist-info/entry_points.txt
reana_cluster-0.3.0.dist-info/top_level.txt
