Metadata-Version: 2.1
Name: reana-cluster
Version: 0.3.0
Summary: REANA-cluster.
Home-page: https://github.com/reanahub/reana-cluster
Author: REANA
Author-email: info@reana.io
License: UNKNOWN
Platform: UNKNOWN
Classifier: Development Status :: 3 - Alpha
Classifier: Environment :: Console
Classifier: Intended Audience :: Developers
Classifier: Intended Audience :: Information Technology
Classifier: License :: OSI Approved :: GNU General Public License v2 (GPLv2)
Classifier: Operating System :: OS Independent
Classifier: Programming Language :: Python :: 2
Classifier: Programming Language :: Python :: 2.7
Classifier: Programming Language :: Python :: 3
Classifier: Programming Language :: Python :: 3.6
Classifier: Programming Language :: Python :: Implementation :: CPython
Classifier: Programming Language :: Python
Classifier: Topic :: System :: Clustering
Classifier: Topic :: System :: Systems Administration
Classifier: Topic :: Utilities
Provides-Extra: docs
Provides-Extra: all
Provides-Extra: tests
Requires-Dist: click (>=6.7)
Requires-Dist: Jinja2 (>=2.9.6)
Requires-Dist: jsonschema (>=2.6.0)
Requires-Dist: kubernetes (>=6.0.0)
Requires-Dist: PyYAML (>=3.12)
Requires-Dist: reana-commons (>=0.3.0)
Requires-Dist: tablib (>=0.12.1)
Requires-Dist: urllib3 (==1.22)
Provides-Extra: all
Requires-Dist: Sphinx (<1.6,>=1.4.4); extra == 'all'
Requires-Dist: sphinx-rtd-theme (>=0.1.9); extra == 'all'
Requires-Dist: sphinx-click (>=1.0.4); extra == 'all'
Requires-Dist: check-manifest (>=0.25); extra == 'all'
Requires-Dist: coverage (>=4.0); extra == 'all'
Requires-Dist: isort (>=4.2.2); extra == 'all'
Requires-Dist: pydocstyle (>=1.0.0); extra == 'all'
Requires-Dist: pytest-cache (>=1.0); extra == 'all'
Requires-Dist: pytest-cov (>=1.8.0); extra == 'all'
Requires-Dist: pytest-pep8 (>=1.0.6); extra == 'all'
Requires-Dist: pytest (>=2.8.0); extra == 'all'
Requires-Dist: Sphinx (<1.6,>=1.4.4); extra == 'all'
Requires-Dist: sphinx-rtd-theme (>=0.1.9); extra == 'all'
Requires-Dist: sphinx-click (>=1.0.4); extra == 'all'
Requires-Dist: check-manifest (>=0.25); extra == 'all'
Requires-Dist: coverage (>=4.0); extra == 'all'
Requires-Dist: isort (>=4.2.2); extra == 'all'
Requires-Dist: pydocstyle (>=1.0.0); extra == 'all'
Requires-Dist: pytest-cache (>=1.0); extra == 'all'
Requires-Dist: pytest-cov (>=1.8.0); extra == 'all'
Requires-Dist: pytest-pep8 (>=1.0.6); extra == 'all'
Requires-Dist: pytest (>=2.8.0); extra == 'all'
Provides-Extra: docs
Requires-Dist: Sphinx (<1.6,>=1.4.4); extra == 'docs'
Requires-Dist: sphinx-rtd-theme (>=0.1.9); extra == 'docs'
Requires-Dist: sphinx-click (>=1.0.4); extra == 'docs'
Provides-Extra: tests
Requires-Dist: check-manifest (>=0.25); extra == 'tests'
Requires-Dist: coverage (>=4.0); extra == 'tests'
Requires-Dist: isort (>=4.2.2); extra == 'tests'
Requires-Dist: pydocstyle (>=1.0.0); extra == 'tests'
Requires-Dist: pytest-cache (>=1.0); extra == 'tests'
Requires-Dist: pytest-cov (>=1.8.0); extra == 'tests'
Requires-Dist: pytest-pep8 (>=1.0.6); extra == 'tests'
Requires-Dist: pytest (>=2.8.0); extra == 'tests'
